agr/__init__.py
agr/config.py
agr/exceptions.py
agr/fetcher.py
agr/handle.py
agr/main.py
agr/metadata.py
agr/skill.py
agr/tool.py
agr/commands/__init__.py
agr/commands/add.py
agr/commands/init.py
agr/commands/list.py
agr/commands/remove.py
agr/commands/sync.py
agr/commands/tools.py
agrx/__init__.py
agrx/main.py
agr-0.7.1.dist-info/METADATA
agr-0.7.1.dist-info/WHEEL
agr-0.7.1.dist-info/entry_points.txt
agr-0.7.1.dist-info/licenses/LICENSE
agr-0.7.1.dist-info/RECORD
