Metadata-Version: 2.4
Name: agr
Version: 0.7.1
Summary: Agent Resources - A package and project manager for AI agents.
License-Expression: MIT
License-File: LICENSE
Requires-Python: >=3.10
Requires-Dist: httpx>=0.27
Requires-Dist: rich>=13.0
Requires-Dist: tomlkit>=0.12
Requires-Dist: typer>=0.12
